shiplibrary/__init__.py
shiplibrary/module_test.py
shiplibrary-0.1.0.dist-info/METADATA
shiplibrary-0.1.0.dist-info/WHEEL
shiplibrary-0.1.0.dist-info/license.txt
shiplibrary-0.1.0.dist-info/top_level.txt
shiplibrary-0.1.0.dist-info/RECORD
